__init__.py
_version.py
iam_credential_rotation.py
provider_aws.py
utils.py
iam_credential_rotation-0.2.2.dist-info/LICENSE
iam_credential_rotation-0.2.2.dist-info/METADATA
iam_credential_rotation-0.2.2.dist-info/WHEEL
iam_credential_rotation-0.2.2.dist-info/entry_points.txt
iam_credential_rotation-0.2.2.dist-info/top_level.txt
iam_credential_rotation-0.2.2.dist-info/RECORD
