Metadata-Version: 2.1
Name: iam-credential-rotation
Version: 0.2.2
Summary: automated rotation for iam machine account programmatic credentials
Author-email: Nic Cheneweth <nchenewe@thoughtworks.com>
Project-URL: Homepage, https://github.com/ThoughtWorks-DPS/iam-credential-rotation
Project-URL: Bug Tracker, https://github.com/ThoughtWorks-DPS/iam-credential-rotation/issues
Classifier: Programming Language :: Python :: 3
Classifier: License :: OSI Approved :: MIT License
Classifier: Operating System :: OS Independent
Requires-Python: >=3.11
License-File: LICENSE
Requires-Dist: click (<9,>=8.1)
Requires-Dist: boto3 (<2,>=1.26.120)
Requires-Dist: pathvalidate (<3,>=2.5.2)
